{
    "名前": "天空の脊",
    "ステータス": {
        "基礎HP": {
            "60+": 0,
            "70": 0,
            "70+": 0,
            "80": 0,
            "80+": 0,
            "90": 0
        },
        "基礎攻撃力": {
            "60+": 455,
            "70": 506,
            "70+": 537,
            "80": 590,
            "80+": 621,
            "90": 674
        },
        "基礎防御力": {
            "60+": 0,
            "70": 0,
            "70+": 0,
            "80": 0,
            "80+": 0,
            "90": 0
        },
        "基礎元素熟知": {
            "60+": 0,
            "70": 0,
            "70+": 0,
            "80": 0,
            "80+": 0,
            "90": 0
        },
        "基礎元素チャージ効率": {
            "60+": 0.271,
            "70": 0.303,
            "70+": 0.303,
            "80": 0.335,
            "80+": 0.335,
            "90": 0.368
        },
        "基礎会心率": {
            "60+": 0,
            "70": 0,
            "70+": 0,
            "80": 0,
            "80+": 0,
            "90": 0
        },
        "基礎会心ダメージ": {
            "60+": 0,
            "70": 0,
            "70+": 0,
            "80": 0,
            "80+": 0,
            "90": 0
        },
        "基礎ダメージバフ": {
            "60+": 0,
            "70": 0,
            "70+": 0,
            "80": 0,
            "80+": 0,
            "90": 0
        },
        "基礎HP％": {
            "60+": 0,
            "70": 0,
            "70+": 0,
            "80": 0,
            "80+": 0,
            "90": 0
        },
        "基礎攻撃力％": {
            "60+": 0,
            "70": 0,
            "70+": 0,
            "80": 0,
            "80+": 0,
            "90": 0
        },
        "基礎防御力％": {
            "60+": 0,
            "70": 0,
            "70+": 0,
            "80": 0,
            "80+": 0,
            "90": 0
        },
        "依存ステータス": [0, 0, 0, 0, 0, 0 ,0]
    }
  }
  